django_sqlite_object_storage/__init__.py
django_sqlite_object_storage/base.py
django_sqlite_object_storage-0.1.2.dist-info/METADATA
django_sqlite_object_storage-0.1.2.dist-info/WHEEL
django_sqlite_object_storage-0.1.2.dist-info/licenses/LICENSE
django_sqlite_object_storage-0.1.2.dist-info/RECORD
