Metadata-Version: 2.3
Name: django-sqlite-object-storage
Version: 0.1.2
Summary: Store an sqlite database in object storage
Project-URL: repository, https://github.com/lukewiwa/django_sqlite_object_storage
Author-email: lukewiwa <luke.wiwa@gmail.com>
License: MIT License
License-File: LICENSE
Classifier: Framework :: Django
Classifier: License :: OSI Approved :: MIT License
Classifier: Operating System :: OS Independent
Classifier: Programming Language :: Python :: 3
Requires-Python: >=3.9
Requires-Dist: boto3>=1.28.79
Requires-Dist: django>=4.2
